pymulproc/__init__.py
pymulproc/errors.py
pymulproc/factory.py
pymulproc/interfaces.py
pymulproc/mpq_protocol.py
pymulproc/pipeapi.py
pymulproc/queuepi.py
pymulproc-0.1.2.dist-info/LICENSE
pymulproc-0.1.2.dist-info/METADATA
pymulproc-0.1.2.dist-info/WHEEL
pymulproc-0.1.2.dist-info/top_level.txt
pymulproc-0.1.2.dist-info/RECORD
