Metadata-Version: 2.1
Name: pymulproc
Version: 0.1.2
Summary: A tiny python library to handle multiprocessing communication
Home-page: https://github.com/d2gex/pymulproc
Author: Dan G
Author-email: daniel.garcia@d2garcia.com
License: UNKNOWN
Platform: UNKNOWN
Classifier: Development Status :: 5 - Production/Stable
Classifier: Environment :: Console
Classifier: Intended Audience :: Developers
Classifier: License :: OSI Approved :: MIT License
Classifier: Operating System :: OS Independent
Classifier: Programming Language :: Python :: 3.6
Classifier: Programming Language :: Python :: 3.7
Classifier: Topic :: Software Development :: Libraries :: Python Modules
Requires-Python: >=3.6
